{
  "type": "Program",
  "start": 0,
  "end": 1480,
  "loc": {
    "start": {
      "line": 1,
      "column": 0
    },
    "end": {
      "line": 68,
      "column": 1
    }
  },
  "sourceType": "module",
  "body": [
    {
      "type": "ImportDeclaration",
      "start": 0,
      "end": 56,
      "loc": {
        "start": {
          "line": 1,
          "column": 0
        },
        "end": {
          "line": 1,
          "column": 56
        }
      },
      "specifiers": [
        {
          "type": "ImportDefaultSpecifier",
          "start": 7,
          "end": 20,
          "loc": {
            "start": {
              "line": 1,
              "column": 7
            },
            "end": {
              "line": 1,
              "column": 20
            }
          },
          "local": {
            "type": "Identifier",
            "start": 7,
            "end": 20,
            "loc": {
              "start": {
                "line": 1,
                "column": 7
              },
              "end": {
                "line": 1,
                "column": 20
              }
            },
            "name": "GCSDispatcher"
          }
        }
      ],
      "importKind": "value",
      "source": {
        "type": "Literal",
        "start": 26,
        "end": 55,
        "loc": {
          "start": {
            "line": 1,
            "column": 26
          },
          "end": {
            "line": 1,
            "column": 55
          }
        },
        "value": "js/dispatcher/GCSDispatcher",
        "rawValue": "js/dispatcher/GCSDispatcher",
        "raw": "'js/dispatcher/GCSDispatcher'"
      }
    },
    {
      "type": "ImportDeclaration",
      "start": 57,
      "end": 114,
      "loc": {
        "start": {
          "line": 2,
          "column": 0
        },
        "end": {
          "line": 2,
          "column": 57
        }
      },
      "specifiers": [
        {
          "type": "ImportSpecifier",
          "start": 66,
          "end": 79,
          "loc": {
            "start": {
              "line": 2,
              "column": 9
            },
            "end": {
              "line": 2,
              "column": 22
            }
          },
          "imported": {
            "type": "Identifier",
            "start": 66,
            "end": 79,
            "loc": {
              "start": {
                "line": 2,
                "column": 9
              },
              "end": {
                "line": 2,
                "column": 22
              }
            },
            "name": "SettingsTypes"
          },
          "local": {
            "type": "Identifier",
            "start": 66,
            "end": 79,
            "loc": {
              "start": {
                "line": 2,
                "column": 9
              },
              "end": {
                "line": 2,
                "column": 22
              }
            },
            "name": "SettingsTypes"
          }
        }
      ],
      "importKind": "value",
      "source": {
        "type": "Literal",
        "start": 87,
        "end": 113,
        "loc": {
          "start": {
            "line": 2,
            "column": 30
          },
          "end": {
            "line": 2,
            "column": 56
          }
        },
        "value": "js/constants/ActionTypes",
        "rawValue": "js/constants/ActionTypes",
        "raw": "'js/constants/ActionTypes'"
      },
      "trailingComments": [
        {
          "type": "Block",
          "value": "*\n * @module actions/SettingsActionCreator\n ",
          "start": 116,
          "end": 164,
          "loc": {
            "start": {
              "line": 4,
              "column": 0
            },
            "end": {
              "line": 6,
              "column": 3
            }
          },
          "range": [
            116,
            164
          ]
        },
        {
          "type": "Block",
          "value": "*\n * Changes the map location value in the store/display \n * Used to move map\n * @param {string} location\n * @returns {undefined}\n ",
          "start": 166,
          "end": 301,
          "loc": {
            "start": {
              "line": 8,
              "column": 0
            },
            "end": {
              "line": 13,
              "column": 3
            }
          },
          "range": [
            166,
            301
          ]
        }
      ]
    },
    {
      "type": "ExportNamedDeclaration",
      "start": 302,
      "end": 435,
      "loc": {
        "start": {
          "line": 14,
          "column": 0
        },
        "end": {
          "line": 19,
          "column": 1
        }
      },
      "declaration": {
        "type": "FunctionDeclaration",
        "start": 309,
        "end": 435,
        "loc": {
          "start": {
            "line": 14,
            "column": 7
          },
          "end": {
            "line": 19,
            "column": 1
          }
        },
        "id": {
          "type": "Identifier",
          "start": 318,
          "end": 333,
          "loc": {
            "start": {
              "line": 14,
              "column": 16
            },
            "end": {
              "line": 14,
              "column": 31
            }
          },
          "name": "receiveLocation",
          "leadingComments": null
        },
        "generator": false,
        "expression": false,
        "async": false,
        "params": [
          {
            "type": "Identifier",
            "start": 334,
            "end": 342,
            "loc": {
              "start": {
                "line": 14,
                "column": 32
              },
              "end": {
                "line": 14,
                "column": 40
              }
            },
            "name": "location"
          }
        ],
        "body": {
          "type": "BlockStatement",
          "start": 344,
          "end": 435,
          "loc": {
            "start": {
              "line": 14,
              "column": 42
            },
            "end": {
              "line": 19,
              "column": 1
            }
          },
          "body": [
            {
              "type": "ExpressionStatement",
              "start": 348,
              "end": 433,
              "loc": {
                "start": {
                  "line": 15,
                  "column": 2
                },
                "end": {
                  "line": 18,
                  "column": 5
                }
              },
              "expression": {
                "type": "CallExpression",
                "start": 348,
                "end": 432,
                "loc": {
                  "start": {
                    "line": 15,
                    "column": 2
                  },
                  "end": {
                    "line": 18,
                    "column": 4
                  }
                },
                "callee": {
                  "type": "MemberExpression",
                  "start": 348,
                  "end": 370,
                  "loc": {
                    "start": {
                      "line": 15,
                      "column": 2
                    },
                    "end": {
                      "line": 15,
                      "column": 24
                    }
                  },
                  "object": {
                    "type": "Identifier",
                    "start": 348,
                    "end": 361,
                    "loc": {
                      "start": {
                        "line": 15,
                        "column": 2
                      },
                      "end": {
                        "line": 15,
                        "column": 15
                      }
                    },
                    "name": "GCSDispatcher"
                  },
                  "property": {
                    "type": "Identifier",
                    "start": 362,
                    "end": 370,
                    "loc": {
                      "start": {
                        "line": 15,
                        "column": 16
                      },
                      "end": {
                        "line": 15,
                        "column": 24
                      }
                    },
                    "name": "dispatch"
                  },
                  "computed": false
                },
                "arguments": [
                  {
                    "type": "ObjectExpression",
                    "start": 371,
                    "end": 431,
                    "loc": {
                      "start": {
                        "line": 15,
                        "column": 25
                      },
                      "end": {
                        "line": 18,
                        "column": 3
                      }
                    },
                    "properties": [
                      {
                        "type": "Property",
                        "start": 377,
                        "end": 413,
                        "loc": {
                          "start": {
                            "line": 16,
                            "column": 4
                          },
                          "end": {
                            "line": 16,
                            "column": 40
                          }
                        },
                        "method": false,
                        "shorthand": false,
                        "computed": false,
                        "key": {
                          "type": "Identifier",
                          "start": 377,
                          "end": 381,
                          "loc": {
                            "start": {
                              "line": 16,
                              "column": 4
                            },
                            "end": {
                              "line": 16,
                              "column": 8
                            }
                          },
                          "name": "type"
                        },
                        "value": {
                          "type": "MemberExpression",
                          "start": 383,
                          "end": 413,
                          "loc": {
                            "start": {
                              "line": 16,
                              "column": 10
                            },
                            "end": {
                              "line": 16,
                              "column": 40
                            }
                          },
                          "object": {
                            "type": "Identifier",
                            "start": 383,
                            "end": 396,
                            "loc": {
                              "start": {
                                "line": 16,
                                "column": 10
                              },
                              "end": {
                                "line": 16,
                                "column": 23
                              }
                            },
                            "name": "SettingsTypes"
                          },
                          "property": {
                            "type": "Identifier",
                            "start": 397,
                            "end": 413,
                            "loc": {
                              "start": {
                                "line": 16,
                                "column": 24
                              },
                              "end": {
                                "line": 16,
                                "column": 40
                              }
                            },
                            "name": "RECEIVE_LOCATION"
                          },
                          "computed": false
                        },
                        "kind": "init"
                      },
                      {
                        "type": "Property",
                        "start": 419,
                        "end": 427,
                        "loc": {
                          "start": {
                            "line": 17,
                            "column": 4
                          },
                          "end": {
                            "line": 17,
                            "column": 12
                          }
                        },
                        "method": false,
                        "shorthand": true,
                        "computed": false,
                        "key": {
                          "type": "Identifier",
                          "start": 419,
                          "end": 427,
                          "loc": {
                            "start": {
                              "line": 17,
                              "column": 4
                            },
                            "end": {
                              "line": 17,
                              "column": 12
                            }
                          },
                          "name": "location"
                        },
                        "kind": "init",
                        "value": {
                          "type": "Identifier",
                          "start": 419,
                          "end": 427,
                          "loc": {
                            "start": {
                              "line": 17,
                              "column": 4
                            },
                            "end": {
                              "line": 17,
                              "column": 12
                            }
                          },
                          "name": "location"
                        }
                      }
                    ]
                  }
                ]
              }
            }
          ],
          "trailingComments": null
        },
        "leadingComments": [
          {
            "type": "Block",
            "value": "*\n * @module actions/SettingsActionCreator\n ",
            "start": 116,
            "end": 164,
            "loc": {
              "start": {
                "line": 4,
                "column": 0
              },
              "end": {
                "line": 6,
                "column": 3
              }
            },
            "range": [
              116,
              164
            ]
          },
          {
            "type": "Block",
            "value": "*\n * Changes the map location value in the store/display \n * Used to move map\n * @param {string} location\n * @returns {undefined}\n ",
            "start": 166,
            "end": 301,
            "loc": {
              "start": {
                "line": 8,
                "column": 0
              },
              "end": {
                "line": 13,
                "column": 3
              }
            },
            "range": [
              166,
              301
            ]
          }
        ],
        "trailingComments": [
          {
            "type": "Block",
            "value": "*\n * Changes store of locations options in settings\n * Used to update location options\n * @param {Object[]} locations\n * @returns {undefined}\n ",
            "start": 437,
            "end": 584,
            "loc": {
              "start": {
                "line": 21,
                "column": 0
              },
              "end": {
                "line": 26,
                "column": 3
              }
            },
            "range": [
              437,
              584
            ]
          }
        ]
      },
      "specifiers": [],
      "source": null,
      "leadingComments": [
        {
          "type": "Block",
          "value": "*\n * @module actions/SettingsActionCreator\n ",
          "start": 116,
          "end": 164,
          "loc": {
            "start": {
              "line": 4,
              "column": 0
            },
            "end": {
              "line": 6,
              "column": 3
            }
          },
          "range": [
            116,
            164
          ]
        },
        {
          "type": "Block",
          "value": "*\n * Changes the map location value in the store/display \n * Used to move map\n * @param {string} location\n * @returns {undefined}\n ",
          "start": 166,
          "end": 301,
          "loc": {
            "start": {
              "line": 8,
              "column": 0
            },
            "end": {
              "line": 13,
              "column": 3
            }
          },
          "range": [
            166,
            301
          ]
        }
      ],
      "trailingComments": [
        {
          "type": "Block",
          "value": "*\n * Changes store of locations options in settings\n * Used to update location options\n * @param {Object[]} locations\n * @returns {undefined}\n ",
          "start": 437,
          "end": 584,
          "loc": {
            "start": {
              "line": 21,
              "column": 0
            },
            "end": {
              "line": 26,
              "column": 3
            }
          },
          "range": [
            437,
            584
          ]
        }
      ]
    },
    {
      "type": "ExportNamedDeclaration",
      "start": 585,
      "end": 722,
      "loc": {
        "start": {
          "line": 27,
          "column": 0
        },
        "end": {
          "line": 32,
          "column": 1
        }
      },
      "declaration": {
        "type": "FunctionDeclaration",
        "start": 592,
        "end": 722,
        "loc": {
          "start": {
            "line": 27,
            "column": 7
          },
          "end": {
            "line": 32,
            "column": 1
          }
        },
        "id": {
          "type": "Identifier",
          "start": 601,
          "end": 617,
          "loc": {
            "start": {
              "line": 27,
              "column": 16
            },
            "end": {
              "line": 27,
              "column": 32
            }
          },
          "name": "receiveLocations",
          "leadingComments": null
        },
        "generator": false,
        "expression": false,
        "async": false,
        "params": [
          {
            "type": "Identifier",
            "start": 618,
            "end": 627,
            "loc": {
              "start": {
                "line": 27,
                "column": 33
              },
              "end": {
                "line": 27,
                "column": 42
              }
            },
            "name": "locations"
          }
        ],
        "body": {
          "type": "BlockStatement",
          "start": 629,
          "end": 722,
          "loc": {
            "start": {
              "line": 27,
              "column": 44
            },
            "end": {
              "line": 32,
              "column": 1
            }
          },
          "body": [
            {
              "type": "ExpressionStatement",
              "start": 633,
              "end": 720,
              "loc": {
                "start": {
                  "line": 28,
                  "column": 2
                },
                "end": {
                  "line": 31,
                  "column": 5
                }
              },
              "expression": {
                "type": "CallExpression",
                "start": 633,
                "end": 719,
                "loc": {
                  "start": {
                    "line": 28,
                    "column": 2
                  },
                  "end": {
                    "line": 31,
                    "column": 4
                  }
                },
                "callee": {
                  "type": "MemberExpression",
                  "start": 633,
                  "end": 655,
                  "loc": {
                    "start": {
                      "line": 28,
                      "column": 2
                    },
                    "end": {
                      "line": 28,
                      "column": 24
                    }
                  },
                  "object": {
                    "type": "Identifier",
                    "start": 633,
                    "end": 646,
                    "loc": {
                      "start": {
                        "line": 28,
                        "column": 2
                      },
                      "end": {
                        "line": 28,
                        "column": 15
                      }
                    },
                    "name": "GCSDispatcher"
                  },
                  "property": {
                    "type": "Identifier",
                    "start": 647,
                    "end": 655,
                    "loc": {
                      "start": {
                        "line": 28,
                        "column": 16
                      },
                      "end": {
                        "line": 28,
                        "column": 24
                      }
                    },
                    "name": "dispatch"
                  },
                  "computed": false
                },
                "arguments": [
                  {
                    "type": "ObjectExpression",
                    "start": 656,
                    "end": 718,
                    "loc": {
                      "start": {
                        "line": 28,
                        "column": 25
                      },
                      "end": {
                        "line": 31,
                        "column": 3
                      }
                    },
                    "properties": [
                      {
                        "type": "Property",
                        "start": 662,
                        "end": 699,
                        "loc": {
                          "start": {
                            "line": 29,
                            "column": 4
                          },
                          "end": {
                            "line": 29,
                            "column": 41
                          }
                        },
                        "method": false,
                        "shorthand": false,
                        "computed": false,
                        "key": {
                          "type": "Identifier",
                          "start": 662,
                          "end": 666,
                          "loc": {
                            "start": {
                              "line": 29,
                              "column": 4
                            },
                            "end": {
                              "line": 29,
                              "column": 8
                            }
                          },
                          "name": "type"
                        },
                        "value": {
                          "type": "MemberExpression",
                          "start": 668,
                          "end": 699,
                          "loc": {
                            "start": {
                              "line": 29,
                              "column": 10
                            },
                            "end": {
                              "line": 29,
                              "column": 41
                            }
                          },
                          "object": {
                            "type": "Identifier",
                            "start": 668,
                            "end": 681,
                            "loc": {
                              "start": {
                                "line": 29,
                                "column": 10
                              },
                              "end": {
                                "line": 29,
                                "column": 23
                              }
                            },
                            "name": "SettingsTypes"
                          },
                          "property": {
                            "type": "Identifier",
                            "start": 682,
                            "end": 699,
                            "loc": {
                              "start": {
                                "line": 29,
                                "column": 24
                              },
                              "end": {
                                "line": 29,
                                "column": 41
                              }
                            },
                            "name": "RECEIVE_LOCATIONS"
                          },
                          "computed": false
                        },
                        "kind": "init"
                      },
                      {
                        "type": "Property",
                        "start": 705,
                        "end": 714,
                        "loc": {
                          "start": {
                            "line": 30,
                            "column": 4
                          },
                          "end": {
                            "line": 30,
                            "column": 13
                          }
                        },
                        "method": false,
                        "shorthand": true,
                        "computed": false,
                        "key": {
                          "type": "Identifier",
                          "start": 705,
                          "end": 714,
                          "loc": {
                            "start": {
                              "line": 30,
                              "column": 4
                            },
                            "end": {
                              "line": 30,
                              "column": 13
                            }
                          },
                          "name": "locations"
                        },
                        "kind": "init",
                        "value": {
                          "type": "Identifier",
                          "start": 705,
                          "end": 714,
                          "loc": {
                            "start": {
                              "line": 30,
                              "column": 4
                            },
                            "end": {
                              "line": 30,
                              "column": 13
                            }
                          },
                          "name": "locations"
                        }
                      }
                    ]
                  }
                ]
              }
            }
          ],
          "trailingComments": null
        },
        "leadingComments": [
          {
            "type": "Block",
            "value": "*\n * Changes store of locations options in settings\n * Used to update location options\n * @param {Object[]} locations\n * @returns {undefined}\n ",
            "start": 437,
            "end": 584,
            "loc": {
              "start": {
                "line": 21,
                "column": 0
              },
              "end": {
                "line": 26,
                "column": 3
              }
            },
            "range": [
              437,
              584
            ]
          }
        ],
        "trailingComments": [
          {
            "type": "Block",
            "value": "*\n * Changes the flight notes\n * @param {string} flight_notes\n * @returns {undefined}\n ",
            "start": 724,
            "end": 815,
            "loc": {
              "start": {
                "line": 34,
                "column": 0
              },
              "end": {
                "line": 38,
                "column": 3
              }
            },
            "range": [
              724,
              815
            ]
          }
        ]
      },
      "specifiers": [],
      "source": null,
      "leadingComments": [
        {
          "type": "Block",
          "value": "*\n * Changes store of locations options in settings\n * Used to update location options\n * @param {Object[]} locations\n * @returns {undefined}\n ",
          "start": 437,
          "end": 584,
          "loc": {
            "start": {
              "line": 21,
              "column": 0
            },
            "end": {
              "line": 26,
              "column": 3
            }
          },
          "range": [
            437,
            584
          ]
        }
      ],
      "trailingComments": [
        {
          "type": "Block",
          "value": "*\n * Changes the flight notes\n * @param {string} flight_notes\n * @returns {undefined}\n ",
          "start": 724,
          "end": 815,
          "loc": {
            "start": {
              "line": 34,
              "column": 0
            },
            "end": {
              "line": 38,
              "column": 3
            }
          },
          "range": [
            724,
            815
          ]
        }
      ]
    },
    {
      "type": "ExportNamedDeclaration",
      "start": 816,
      "end": 964,
      "loc": {
        "start": {
          "line": 39,
          "column": 0
        },
        "end": {
          "line": 44,
          "column": 1
        }
      },
      "declaration": {
        "type": "FunctionDeclaration",
        "start": 823,
        "end": 964,
        "loc": {
          "start": {
            "line": 39,
            "column": 7
          },
          "end": {
            "line": 44,
            "column": 1
          }
        },
        "id": {
          "type": "Identifier",
          "start": 832,
          "end": 850,
          "loc": {
            "start": {
              "line": 39,
              "column": 16
            },
            "end": {
              "line": 39,
              "column": 34
            }
          },
          "name": "receiveFlightNotes",
          "leadingComments": null
        },
        "generator": false,
        "expression": false,
        "async": false,
        "params": [
          {
            "type": "Identifier",
            "start": 851,
            "end": 863,
            "loc": {
              "start": {
                "line": 39,
                "column": 35
              },
              "end": {
                "line": 39,
                "column": 47
              }
            },
            "name": "flight_notes"
          }
        ],
        "body": {
          "type": "BlockStatement",
          "start": 865,
          "end": 964,
          "loc": {
            "start": {
              "line": 39,
              "column": 49
            },
            "end": {
              "line": 44,
              "column": 1
            }
          },
          "body": [
            {
              "type": "ExpressionStatement",
              "start": 869,
              "end": 962,
              "loc": {
                "start": {
                  "line": 40,
                  "column": 2
                },
                "end": {
                  "line": 43,
                  "column": 5
                }
              },
              "expression": {
                "type": "CallExpression",
                "start": 869,
                "end": 961,
                "loc": {
                  "start": {
                    "line": 40,
                    "column": 2
                  },
                  "end": {
                    "line": 43,
                    "column": 4
                  }
                },
                "callee": {
                  "type": "MemberExpression",
                  "start": 869,
                  "end": 891,
                  "loc": {
                    "start": {
                      "line": 40,
                      "column": 2
                    },
                    "end": {
                      "line": 40,
                      "column": 24
                    }
                  },
                  "object": {
                    "type": "Identifier",
                    "start": 869,
                    "end": 882,
                    "loc": {
                      "start": {
                        "line": 40,
                        "column": 2
                      },
                      "end": {
                        "line": 40,
                        "column": 15
                      }
                    },
                    "name": "GCSDispatcher"
                  },
                  "property": {
                    "type": "Identifier",
                    "start": 883,
                    "end": 891,
                    "loc": {
                      "start": {
                        "line": 40,
                        "column": 16
                      },
                      "end": {
                        "line": 40,
                        "column": 24
                      }
                    },
                    "name": "dispatch"
                  },
                  "computed": false
                },
                "arguments": [
                  {
                    "type": "ObjectExpression",
                    "start": 892,
                    "end": 960,
                    "loc": {
                      "start": {
                        "line": 40,
                        "column": 25
                      },
                      "end": {
                        "line": 43,
                        "column": 3
                      }
                    },
                    "properties": [
                      {
                        "type": "Property",
                        "start": 898,
                        "end": 938,
                        "loc": {
                          "start": {
                            "line": 41,
                            "column": 4
                          },
                          "end": {
                            "line": 41,
                            "column": 44
                          }
                        },
                        "method": false,
                        "shorthand": false,
                        "computed": false,
                        "key": {
                          "type": "Identifier",
                          "start": 898,
                          "end": 902,
                          "loc": {
                            "start": {
                              "line": 41,
                              "column": 4
                            },
                            "end": {
                              "line": 41,
                              "column": 8
                            }
                          },
                          "name": "type"
                        },
                        "value": {
                          "type": "MemberExpression",
                          "start": 904,
                          "end": 938,
                          "loc": {
                            "start": {
                              "line": 41,
                              "column": 10
                            },
                            "end": {
                              "line": 41,
                              "column": 44
                            }
                          },
                          "object": {
                            "type": "Identifier",
                            "start": 904,
                            "end": 917,
                            "loc": {
                              "start": {
                                "line": 41,
                                "column": 10
                              },
                              "end": {
                                "line": 41,
                                "column": 23
                              }
                            },
                            "name": "SettingsTypes"
                          },
                          "property": {
                            "type": "Identifier",
                            "start": 918,
                            "end": 938,
                            "loc": {
                              "start": {
                                "line": 41,
                                "column": 24
                              },
                              "end": {
                                "line": 41,
                                "column": 44
                              }
                            },
                            "name": "RECEIVE_FLIGHT_NOTES"
                          },
                          "computed": false
                        },
                        "kind": "init"
                      },
                      {
                        "type": "Property",
                        "start": 944,
                        "end": 956,
                        "loc": {
                          "start": {
                            "line": 42,
                            "column": 4
                          },
                          "end": {
                            "line": 42,
                            "column": 16
                          }
                        },
                        "method": false,
                        "shorthand": true,
                        "computed": false,
                        "key": {
                          "type": "Identifier",
                          "start": 944,
                          "end": 956,
                          "loc": {
                            "start": {
                              "line": 42,
                              "column": 4
                            },
                            "end": {
                              "line": 42,
                              "column": 16
                            }
                          },
                          "name": "flight_notes"
                        },
                        "kind": "init",
                        "value": {
                          "type": "Identifier",
                          "start": 944,
                          "end": 956,
                          "loc": {
                            "start": {
                              "line": 42,
                              "column": 4
                            },
                            "end": {
                              "line": 42,
                              "column": 16
                            }
                          },
                          "name": "flight_notes"
                        }
                      }
                    ]
                  }
                ]
              }
            }
          ],
          "trailingComments": null
        },
        "leadingComments": [
          {
            "type": "Block",
            "value": "*\n * Changes the flight notes\n * @param {string} flight_notes\n * @returns {undefined}\n ",
            "start": 724,
            "end": 815,
            "loc": {
              "start": {
                "line": 34,
                "column": 0
              },
              "end": {
                "line": 38,
                "column": 3
              }
            },
            "range": [
              724,
              815
            ]
          }
        ],
        "trailingComments": [
          {
            "type": "Block",
            "value": "*\n * Changes whether the unit switch is metric (true) or US customary (false)\n * @param {boolean} value\n * @returns {undefined}\n ",
            "start": 966,
            "end": 1099,
            "loc": {
              "start": {
                "line": 46,
                "column": 0
              },
              "end": {
                "line": 50,
                "column": 3
              }
            },
            "range": [
              966,
              1099
            ]
          }
        ]
      },
      "specifiers": [],
      "source": null,
      "leadingComments": [
        {
          "type": "Block",
          "value": "*\n * Changes the flight notes\n * @param {string} flight_notes\n * @returns {undefined}\n ",
          "start": 724,
          "end": 815,
          "loc": {
            "start": {
              "line": 34,
              "column": 0
            },
            "end": {
              "line": 38,
              "column": 3
            }
          },
          "range": [
            724,
            815
          ]
        }
      ],
      "trailingComments": [
        {
          "type": "Block",
          "value": "*\n * Changes whether the unit switch is metric (true) or US customary (false)\n * @param {boolean} value\n * @returns {undefined}\n ",
          "start": 966,
          "end": 1099,
          "loc": {
            "start": {
              "line": 46,
              "column": 0
            },
            "end": {
              "line": 50,
              "column": 3
            }
          },
          "range": [
            966,
            1099
          ]
        }
      ]
    },
    {
      "type": "ExportNamedDeclaration",
      "start": 1100,
      "end": 1217,
      "loc": {
        "start": {
          "line": 51,
          "column": 0
        },
        "end": {
          "line": 56,
          "column": 1
        }
      },
      "declaration": {
        "type": "FunctionDeclaration",
        "start": 1107,
        "end": 1217,
        "loc": {
          "start": {
            "line": 51,
            "column": 7
          },
          "end": {
            "line": 56,
            "column": 1
          }
        },
        "id": {
          "type": "Identifier",
          "start": 1116,
          "end": 1126,
          "loc": {
            "start": {
              "line": 51,
              "column": 16
            },
            "end": {
              "line": 51,
              "column": 26
            }
          },
          "name": "unitSwitch",
          "leadingComments": null
        },
        "generator": false,
        "expression": false,
        "async": false,
        "params": [
          {
            "type": "Identifier",
            "start": 1127,
            "end": 1132,
            "loc": {
              "start": {
                "line": 51,
                "column": 27
              },
              "end": {
                "line": 51,
                "column": 32
              }
            },
            "name": "value"
          }
        ],
        "body": {
          "type": "BlockStatement",
          "start": 1134,
          "end": 1217,
          "loc": {
            "start": {
              "line": 51,
              "column": 34
            },
            "end": {
              "line": 56,
              "column": 1
            }
          },
          "body": [
            {
              "type": "ExpressionStatement",
              "start": 1138,
              "end": 1215,
              "loc": {
                "start": {
                  "line": 52,
                  "column": 2
                },
                "end": {
                  "line": 55,
                  "column": 5
                }
              },
              "expression": {
                "type": "CallExpression",
                "start": 1138,
                "end": 1214,
                "loc": {
                  "start": {
                    "line": 52,
                    "column": 2
                  },
                  "end": {
                    "line": 55,
                    "column": 4
                  }
                },
                "callee": {
                  "type": "MemberExpression",
                  "start": 1138,
                  "end": 1160,
                  "loc": {
                    "start": {
                      "line": 52,
                      "column": 2
                    },
                    "end": {
                      "line": 52,
                      "column": 24
                    }
                  },
                  "object": {
                    "type": "Identifier",
                    "start": 1138,
                    "end": 1151,
                    "loc": {
                      "start": {
                        "line": 52,
                        "column": 2
                      },
                      "end": {
                        "line": 52,
                        "column": 15
                      }
                    },
                    "name": "GCSDispatcher"
                  },
                  "property": {
                    "type": "Identifier",
                    "start": 1152,
                    "end": 1160,
                    "loc": {
                      "start": {
                        "line": 52,
                        "column": 16
                      },
                      "end": {
                        "line": 52,
                        "column": 24
                      }
                    },
                    "name": "dispatch"
                  },
                  "computed": false
                },
                "arguments": [
                  {
                    "type": "ObjectExpression",
                    "start": 1161,
                    "end": 1213,
                    "loc": {
                      "start": {
                        "line": 52,
                        "column": 25
                      },
                      "end": {
                        "line": 55,
                        "column": 3
                      }
                    },
                    "properties": [
                      {
                        "type": "Property",
                        "start": 1167,
                        "end": 1198,
                        "loc": {
                          "start": {
                            "line": 53,
                            "column": 4
                          },
                          "end": {
                            "line": 53,
                            "column": 35
                          }
                        },
                        "method": false,
                        "shorthand": false,
                        "computed": false,
                        "key": {
                          "type": "Identifier",
                          "start": 1167,
                          "end": 1171,
                          "loc": {
                            "start": {
                              "line": 53,
                              "column": 4
                            },
                            "end": {
                              "line": 53,
                              "column": 8
                            }
                          },
                          "name": "type"
                        },
                        "value": {
                          "type": "MemberExpression",
                          "start": 1173,
                          "end": 1198,
                          "loc": {
                            "start": {
                              "line": 53,
                              "column": 10
                            },
                            "end": {
                              "line": 53,
                              "column": 35
                            }
                          },
                          "object": {
                            "type": "Identifier",
                            "start": 1173,
                            "end": 1186,
                            "loc": {
                              "start": {
                                "line": 53,
                                "column": 10
                              },
                              "end": {
                                "line": 53,
                                "column": 23
                              }
                            },
                            "name": "SettingsTypes"
                          },
                          "property": {
                            "type": "Identifier",
                            "start": 1187,
                            "end": 1198,
                            "loc": {
                              "start": {
                                "line": 53,
                                "column": 24
                              },
                              "end": {
                                "line": 53,
                                "column": 35
                              }
                            },
                            "name": "UNIT_SWITCH"
                          },
                          "computed": false
                        },
                        "kind": "init"
                      },
                      {
                        "type": "Property",
                        "start": 1204,
                        "end": 1209,
                        "loc": {
                          "start": {
                            "line": 54,
                            "column": 4
                          },
                          "end": {
                            "line": 54,
                            "column": 9
                          }
                        },
                        "method": false,
                        "shorthand": true,
                        "computed": false,
                        "key": {
                          "type": "Identifier",
                          "start": 1204,
                          "end": 1209,
                          "loc": {
                            "start": {
                              "line": 54,
                              "column": 4
                            },
                            "end": {
                              "line": 54,
                              "column": 9
                            }
                          },
                          "name": "value"
                        },
                        "kind": "init",
                        "value": {
                          "type": "Identifier",
                          "start": 1204,
                          "end": 1209,
                          "loc": {
                            "start": {
                              "line": 54,
                              "column": 4
                            },
                            "end": {
                              "line": 54,
                              "column": 9
                            }
                          },
                          "name": "value"
                        }
                      }
                    ]
                  }
                ]
              }
            }
          ],
          "trailingComments": null
        },
        "leadingComments": [
          {
            "type": "Block",
            "value": "*\n * Changes whether the unit switch is metric (true) or US customary (false)\n * @param {boolean} value\n * @returns {undefined}\n ",
            "start": 966,
            "end": 1099,
            "loc": {
              "start": {
                "line": 46,
                "column": 0
              },
              "end": {
                "line": 50,
                "column": 3
              }
            },
            "range": [
              966,
              1099
            ]
          }
        ],
        "trailingComments": [
          {
            "type": "Block",
            "value": "*\n * Changes whether the the slider is historical (or current)\n * @param {boolean} value\n * @returns {undefined}\n ",
            "start": 1219,
            "end": 1337,
            "loc": {
              "start": {
                "line": 58,
                "column": 0
              },
              "end": {
                "line": 62,
                "column": 3
              }
            },
            "range": [
              1219,
              1337
            ]
          }
        ]
      },
      "specifiers": [],
      "source": null,
      "leadingComments": [
        {
          "type": "Block",
          "value": "*\n * Changes whether the unit switch is metric (true) or US customary (false)\n * @param {boolean} value\n * @returns {undefined}\n ",
          "start": 966,
          "end": 1099,
          "loc": {
            "start": {
              "line": 46,
              "column": 0
            },
            "end": {
              "line": 50,
              "column": 3
            }
          },
          "range": [
            966,
            1099
          ]
        }
      ],
      "trailingComments": [
        {
          "type": "Block",
          "value": "*\n * Changes whether the the slider is historical (or current)\n * @param {boolean} value\n * @returns {undefined}\n ",
          "start": 1219,
          "end": 1337,
          "loc": {
            "start": {
              "line": 58,
              "column": 0
            },
            "end": {
              "line": 62,
              "column": 3
            }
          },
          "range": [
            1219,
            1337
          ]
        }
      ]
    },
    {
      "type": "ExportNamedDeclaration",
      "start": 1338,
      "end": 1480,
      "loc": {
        "start": {
          "line": 63,
          "column": 0
        },
        "end": {
          "line": 68,
          "column": 1
        }
      },
      "declaration": {
        "type": "FunctionDeclaration",
        "start": 1345,
        "end": 1480,
        "loc": {
          "start": {
            "line": 63,
            "column": 7
          },
          "end": {
            "line": 68,
            "column": 1
          }
        },
        "id": {
          "type": "Identifier",
          "start": 1354,
          "end": 1376,
          "loc": {
            "start": {
              "line": 63,
              "column": 16
            },
            "end": {
              "line": 63,
              "column": 38
            }
          },
          "name": "changeHistoricalSlider",
          "leadingComments": null
        },
        "generator": false,
        "expression": false,
        "async": false,
        "params": [
          {
            "type": "Identifier",
            "start": 1377,
            "end": 1382,
            "loc": {
              "start": {
                "line": 63,
                "column": 39
              },
              "end": {
                "line": 63,
                "column": 44
              }
            },
            "name": "value"
          }
        ],
        "body": {
          "type": "BlockStatement",
          "start": 1384,
          "end": 1480,
          "loc": {
            "start": {
              "line": 63,
              "column": 46
            },
            "end": {
              "line": 68,
              "column": 1
            }
          },
          "body": [
            {
              "type": "ExpressionStatement",
              "start": 1388,
              "end": 1478,
              "loc": {
                "start": {
                  "line": 64,
                  "column": 2
                },
                "end": {
                  "line": 67,
                  "column": 5
                }
              },
              "expression": {
                "type": "CallExpression",
                "start": 1388,
                "end": 1477,
                "loc": {
                  "start": {
                    "line": 64,
                    "column": 2
                  },
                  "end": {
                    "line": 67,
                    "column": 4
                  }
                },
                "callee": {
                  "type": "MemberExpression",
                  "start": 1388,
                  "end": 1410,
                  "loc": {
                    "start": {
                      "line": 64,
                      "column": 2
                    },
                    "end": {
                      "line": 64,
                      "column": 24
                    }
                  },
                  "object": {
                    "type": "Identifier",
                    "start": 1388,
                    "end": 1401,
                    "loc": {
                      "start": {
                        "line": 64,
                        "column": 2
                      },
                      "end": {
                        "line": 64,
                        "column": 15
                      }
                    },
                    "name": "GCSDispatcher"
                  },
                  "property": {
                    "type": "Identifier",
                    "start": 1402,
                    "end": 1410,
                    "loc": {
                      "start": {
                        "line": 64,
                        "column": 16
                      },
                      "end": {
                        "line": 64,
                        "column": 24
                      }
                    },
                    "name": "dispatch"
                  },
                  "computed": false
                },
                "arguments": [
                  {
                    "type": "ObjectExpression",
                    "start": 1411,
                    "end": 1476,
                    "loc": {
                      "start": {
                        "line": 64,
                        "column": 25
                      },
                      "end": {
                        "line": 67,
                        "column": 3
                      }
                    },
                    "properties": [
                      {
                        "type": "Property",
                        "start": 1417,
                        "end": 1461,
                        "loc": {
                          "start": {
                            "line": 65,
                            "column": 4
                          },
                          "end": {
                            "line": 65,
                            "column": 48
                          }
                        },
                        "method": false,
                        "shorthand": false,
                        "computed": false,
                        "key": {
                          "type": "Identifier",
                          "start": 1417,
                          "end": 1421,
                          "loc": {
                            "start": {
                              "line": 65,
                              "column": 4
                            },
                            "end": {
                              "line": 65,
                              "column": 8
                            }
                          },
                          "name": "type"
                        },
                        "value": {
                          "type": "MemberExpression",
                          "start": 1423,
                          "end": 1461,
                          "loc": {
                            "start": {
                              "line": 65,
                              "column": 10
                            },
                            "end": {
                              "line": 65,
                              "column": 48
                            }
                          },
                          "object": {
                            "type": "Identifier",
                            "start": 1423,
                            "end": 1436,
                            "loc": {
                              "start": {
                                "line": 65,
                                "column": 10
                              },
                              "end": {
                                "line": 65,
                                "column": 23
                              }
                            },
                            "name": "SettingsTypes"
                          },
                          "property": {
                            "type": "Identifier",
                            "start": 1437,
                            "end": 1461,
                            "loc": {
                              "start": {
                                "line": 65,
                                "column": 24
                              },
                              "end": {
                                "line": 65,
                                "column": 48
                              }
                            },
                            "name": "CHANGE_HISTORICAL_SLIDER"
                          },
                          "computed": false
                        },
                        "kind": "init"
                      },
                      {
                        "type": "Property",
                        "start": 1467,
                        "end": 1472,
                        "loc": {
                          "start": {
                            "line": 66,
                            "column": 4
                          },
                          "end": {
                            "line": 66,
                            "column": 9
                          }
                        },
                        "method": false,
                        "shorthand": true,
                        "computed": false,
                        "key": {
                          "type": "Identifier",
                          "start": 1467,
                          "end": 1472,
                          "loc": {
                            "start": {
                              "line": 66,
                              "column": 4
                            },
                            "end": {
                              "line": 66,
                              "column": 9
                            }
                          },
                          "name": "value"
                        },
                        "kind": "init",
                        "value": {
                          "type": "Identifier",
                          "start": 1467,
                          "end": 1472,
                          "loc": {
                            "start": {
                              "line": 66,
                              "column": 4
                            },
                            "end": {
                              "line": 66,
                              "column": 9
                            }
                          },
                          "name": "value"
                        }
                      }
                    ]
                  }
                ]
              }
            }
          ]
        },
        "leadingComments": [
          {
            "type": "Block",
            "value": "*\n * Changes whether the the slider is historical (or current)\n * @param {boolean} value\n * @returns {undefined}\n ",
            "start": 1219,
            "end": 1337,
            "loc": {
              "start": {
                "line": 58,
                "column": 0
              },
              "end": {
                "line": 62,
                "column": 3
              }
            },
            "range": [
              1219,
              1337
            ]
          }
        ],
        "trailingComments": []
      },
      "specifiers": [],
      "source": null,
      "leadingComments": [
        {
          "type": "Block",
          "value": "*\n * Changes whether the the slider is historical (or current)\n * @param {boolean} value\n * @returns {undefined}\n ",
          "start": 1219,
          "end": 1337,
          "loc": {
            "start": {
              "line": 58,
              "column": 0
            },
            "end": {
              "line": 62,
              "column": 3
            }
          },
          "range": [
            1219,
            1337
          ]
        }
      ]
    }
  ]
}